hanzo_tools/__init__.py
hanzo_tools/llm/__init__.py
hanzo_tools/llm/consensus_tool.py
hanzo_tools/llm/llm_manage.py
hanzo_tools/llm/llm_unified.py
hanzo_tools/llm/provider_tools.py
hanzo_tools_llm-0.2.0.dist-info/METADATA
hanzo_tools_llm-0.2.0.dist-info/WHEEL
hanzo_tools_llm-0.2.0.dist-info/entry_points.txt
hanzo_tools_llm-0.2.0.dist-info/top_level.txt
hanzo_tools_llm-0.2.0.dist-info/RECORD
