Metadata-Version: 2.4
Name: hanzo-tools-llm
Version: 0.2.0
Summary: LLM tools for Hanzo AI - model management, consensus, providers
Author-email: Hanzo Industries Inc <dev@hanzo.ai>
License: MIT
Keywords: hanzo,tools,llm,mcp,ai
Requires-Python: >=3.12
Requires-Dist: hanzo-tools-core>=0.1.0
Requires-Dist: mcp>=1.25.0
Requires-Dist: fastmcp>=2.14.1
Requires-Dist: pydantic>=2.12.5
Provides-Extra: full
Requires-Dist: litellm>=1.0.0; extra == "full"
Requires-Dist: openai>=1.0.0; extra == "full"
Requires-Dist: anthropic>=0.40.0; extra == "full"
